pyfesom2/__init__.py
pyfesom2/accessor.py
pyfesom2/ascii_to_netcdf.py
pyfesom2/climatology.py
pyfesom2/config.py
pyfesom2/datasets.py
pyfesom2/diagnostics.py
pyfesom2/fesom2GeoFormat.py
pyfesom2/load_mesh_data.py
pyfesom2/pfinterp.py
pyfesom2/pfplot.py
pyfesom2/plotting.py
pyfesom2/pyfesom2.py
pyfesom2/regridding.py
pyfesom2/transect.py
pyfesom2/transport.py
pyfesom2/ut.py
pyfesom2/geojson/MOCBasins.geojson
pyfesom2/geojson/NinoRegions.geojson
pyfesom2/geojson/oceanBasins.geojson
pyfesom2-0.4.1.dist-info/LICENSE
pyfesom2-0.4.1.dist-info/METADATA
pyfesom2-0.4.1.dist-info/WHEEL
pyfesom2-0.4.1.dist-info/entry_points.txt
pyfesom2-0.4.1.dist-info/top_level.txt
pyfesom2-0.4.1.dist-info/RECORD
