Metadata-Version: 2.1
Name: pyfesom2
Version: 0.4.1
Summary: FESOM2 tools
Home-page: https://github.com/koldunovn/pyfesom2
Download-URL: https://github.com/FESOM/pyfesom2/archive/0.2.0.tar.gz
Author: FESOM team
Author-email: koldunovn@gmail.com
License: MIT license
Keywords: pyfesom2
Classifier: Development Status :: 2 - Pre-Alpha
Classifier: Intended Audience :: Developers
Classifier: License :: OSI Approved :: MIT License
Classifier: Natural Language :: English
Classifier: Programming Language :: Python :: 3
Classifier: Programming Language :: Python :: 3.6
Classifier: Programming Language :: Python :: 3.7
Classifier: Programming Language :: Python :: 3.8
License-File: LICENSE
Requires-Dist: cartopy
Requires-Dist: cmocean
Requires-Dist: dask
Requires-Dist: ipython
Requires-Dist: joblib
Requires-Dist: jupyter
Requires-Dist: matplotlib
Requires-Dist: netCDF4
Requires-Dist: numba
Requires-Dist: numpy
Requires-Dist: pandas
Requires-Dist: pymap3d
Requires-Dist: pyproj
Requires-Dist: pyresample
Requires-Dist: pytest
Requires-Dist: scipy
Requires-Dist: seawater
Requires-Dist: shapely
Requires-Dist: tqdm
Requires-Dist: xarray
